[
    {
        "created": "20250508140222213",
        "text": "<$vue-flow filter=\"[[Plugins]] [[Home]] [[tags]]\" />",
        "tags": "",
        "title": "DEMO",
        "modified": "20250508143224466",
        "type": "text/vnd.tiddlywiki",
        "_edges": "[\n  {\n    \"id\": \"e-tiddler_0-tiddler_1\",\n    \"type\": \"default\",\n    \"source\": \"tiddler_0\",\n    \"target\": \"tiddler_1\",\n    \"data\": {},\n    \"events\": {},\n    \"label\": \"\",\n    \"animated\": true,\n    \"style\": {\n      \"stroke\": \"#1890ff\",\n      \"strokeWidth\": 2\n    },\n    \"markerEnd\": {\n      \"type\": \"arrowclosed\",\n      \"color\": \"#1890ff\",\n      \"width\": 16,\n      \"height\": 16,\n      \"strokeWidth\": 0.1\n    },\n    \"sourceNode\": {\n      \"id\": \"tiddler_0\",\n      \"type\": \"data\",\n      \"dimensions\": {\n        \"width\": 300,\n        \"height\": 121\n      },\n      \"computedPosition\": {\n        \"x\": 20,\n        \"y\": 20,\n        \"z\": 0\n      },\n      \"handleBounds\": {\n        \"source\": [\n          {\n            \"id\": null,\n            \"type\": \"source\",\n            \"nodeId\": \"tiddler_0\",\n            \"position\": \"right\",\n            \"x\": 295.3333282470703,\n            \"y\": 56.333343505859375,\n            \"width\": 8,\n            \"height\": 8\n          }\n        ],\n        \"target\": [\n          {\n            \"id\": null,\n            \"type\": \"target\",\n            \"nodeId\": \"tiddler_0\",\n            \"position\": \"left\",\n            \"x\": -3.3333358764648438,\n            \"y\": 56.333343505859375,\n            \"width\": 8,\n            \"height\": 8\n          }\n        ]\n      },\n      \"selected\": false,\n      \"dragging\": false,\n      \"resizing\": false,\n      \"initialized\": false,\n      \"isParent\": false,\n      \"position\": {\n        \"x\": 20,\n        \"y\": 20\n      },\n      \"data\": {\n        \"label\": \"Plugins\",\n        \"dataType\": \"Tiddler\",\n        \"fields\": {\n          \"title\": \"Plugins\",\n          \"tags\": []\n        }\n      },\n      \"events\": {}\n    },\n    \"targetNode\": {\n      \"id\": \"tiddler_1\",\n      \"type\": \"data\",\n      \"dimensions\": {\n        \"width\": 300,\n        \"height\": 121\n      },\n      \"computedPosition\": {\n        \"x\": 420,\n        \"y\": 20,\n        \"z\": 0\n      },\n      \"handleBounds\": {\n        \"source\": [\n          {\n            \"id\": null,\n            \"type\": \"source\",\n            \"nodeId\": \"tiddler_1\",\n            \"position\": \"right\",\n            \"x\": 295.3333282470703,\n            \"y\": 56.33331298828125,\n            \"width\": 8,\n            \"height\": 8\n          }\n        ],\n        \"target\": [\n          {\n            \"id\": null,\n            \"type\": \"target\",\n            \"nodeId\": \"tiddler_1\",\n            \"position\": \"left\",\n            \"x\": -3.3333358764648438,\n            \"y\": 56.33331298828125,\n            \"width\": 8,\n            \"height\": 8\n          }\n        ]\n      },\n      \"selected\": false,\n      \"dragging\": false,\n      \"resizing\": false,\n      \"initialized\": false,\n      \"isParent\": false,\n      \"position\": {\n        \"x\": 420,\n        \"y\": 20\n      },\n      \"data\": {\n        \"label\": \"Home\",\n        \"dataType\": \"Tiddler\",\n        \"fields\": {\n          \"title\": \"Home\",\n          \"tags\": []\n        }\n      },\n      \"events\": {}\n    },\n    \"sourceX\": 323.3333282470703,\n    \"sourceY\": 80.33334350585938,\n    \"targetX\": 416.66666412353516,\n    \"targetY\": 80.33331298828125\n  }\n]",
        "_nodes": "[\n  {\n    \"id\": \"tiddler_0\",\n    \"type\": \"data\",\n    \"dimensions\": {\n      \"width\": 300,\n      \"height\": 121\n    },\n    \"computedPosition\": {\n      \"x\": 20,\n      \"y\": 20,\n      \"z\": 0\n    },\n    \"handleBounds\": {\n      \"source\": [\n        {\n          \"id\": null,\n          \"type\": \"source\",\n          \"nodeId\": \"tiddler_0\",\n          \"position\": \"right\",\n          \"x\": 295.3333282470703,\n          \"y\": 56.333343505859375,\n          \"width\": 8,\n          \"height\": 8\n        }\n      ],\n      \"target\": [\n        {\n          \"id\": null,\n          \"type\": \"target\",\n          \"nodeId\": \"tiddler_0\",\n          \"position\": \"left\",\n          \"x\": -3.3333358764648438,\n          \"y\": 56.333343505859375,\n          \"width\": 8,\n          \"height\": 8\n        }\n      ]\n    },\n    \"selected\": false,\n    \"dragging\": false,\n    \"resizing\": false,\n    \"initialized\": false,\n    \"isParent\": false,\n    \"position\": {\n      \"x\": 20,\n      \"y\": 20\n    },\n    \"data\": {\n      \"label\": \"Plugins\",\n      \"dataType\": \"Tiddler\",\n      \"fields\": {\n        \"title\": \"Plugins\",\n        \"tags\": []\n      }\n    },\n    \"events\": {}\n  },\n  {\n    \"id\": \"tiddler_1\",\n    \"type\": \"data\",\n    \"dimensions\": {\n      \"width\": 300,\n      \"height\": 121\n    },\n    \"computedPosition\": {\n      \"x\": 420,\n      \"y\": 20,\n      \"z\": 0\n    },\n    \"handleBounds\": {\n      \"source\": [\n        {\n          \"id\": null,\n          \"type\": \"source\",\n          \"nodeId\": \"tiddler_1\",\n          \"position\": \"right\",\n          \"x\": 295.3333282470703,\n          \"y\": 56.33331298828125,\n          \"width\": 8,\n          \"height\": 8\n        }\n      ],\n      \"target\": [\n        {\n          \"id\": null,\n          \"type\": \"target\",\n          \"nodeId\": \"tiddler_1\",\n          \"position\": \"left\",\n          \"x\": -3.3333358764648438,\n          \"y\": 56.33331298828125,\n          \"width\": 8,\n          \"height\": 8\n        }\n      ]\n    },\n    \"selected\": false,\n    \"dragging\": false,\n    \"resizing\": false,\n    \"initialized\": false,\n    \"isParent\": false,\n    \"position\": {\n      \"x\": 420,\n      \"y\": 20\n    },\n    \"data\": {\n      \"label\": \"Home\",\n      \"dataType\": \"Tiddler\",\n      \"fields\": {\n        \"title\": \"Home\",\n        \"tags\": []\n      }\n    },\n    \"events\": {}\n  }\n]"
    }
]